aiopvpc/__init__.py
aiopvpc/const.py
aiopvpc/ha_helpers.py
aiopvpc/parser.py
aiopvpc/prices.py
aiopvpc/pvpc_data.py
aiopvpc/pvpc_tariff.py
aiopvpc/utils.py
aiopvpc-4.3.1.dist-info/LICENSE
aiopvpc-4.3.1.dist-info/METADATA
aiopvpc-4.3.1.dist-info/WHEEL
aiopvpc-4.3.1.dist-info/RECORD
