Metadata-Version: 2.1
Name: aiopvpc
Version: 4.3.1
Summary: Retrieval of Spanish Electricity hourly prices (PVPC)
Home-page: https://github.com/azogue/aiopvpc
License: MIT
Author: Eugenio Panadero
Author-email: eugenio.panadero@gmail.com
Requires-Python: >=3.9
Classifier: License :: OSI Approved :: MIT License
Classifier: Programming Language :: Python :: 3
Classifier: Programming Language :: Python :: 3.9
Classifier: Programming Language :: Python :: 3.10
Classifier: Programming Language :: Python :: 3.11
Classifier: Programming Language :: Python :: 3.12
Requires-Dist: aiohttp (>=3.7.4.post0)
Requires-Dist: async_timeout (>=3.0.1)
Project-URL: Repository, https://github.com/azogue/aiopvpc
